modelcub/__init__.py
modelcub/cli.py
modelcub/commands/about.py
modelcub/commands/init.py
modelcub-0.0.2.dist-info/METADATA
modelcub-0.0.2.dist-info/WHEEL
modelcub-0.0.2.dist-info/entry_points.txt
modelcub-0.0.2.dist-info/top_level.txt
modelcub-0.0.2.dist-info/RECORD
