Metadata-Version: 2.4
Name: modelcub
Version: 0.0.2
Summary: Train and deploy AI models in minutes — zero config.
Author: Seif Boukerdenna
License: MIT
Requires-Python: >=3.9
